{"title":"linux学习笔记","uid":"c42ea271ec848445301016f3b979e666","slug":"linux学习笔记","date":"2022-03-29T15:15:42.000Z","updated":"2022-03-29T15:18:37.714Z","comments":true,"path":"api/articles/linux学习笔记.json","keywords":null,"cover":[],"content":"<p><img src=\"https://img-blog.csdnimg.cn/20210429233210638.png?x-oss-process=image/watermark,type_ZmFuZ3poZW5naGVpdGk,shadow_10,text_aHR0cHM6Ly9ibG9nLmNzZG4ubmV0L2NlbmNlcl9oZWFydA==,size_16,color_FFFFFF,t_70\" alt=\"在这里插入图片描述\"><br><img src=\"https://img-blog.csdnimg.cn/20210429233419606.png?x-oss-process=image/watermark,type_ZmFuZ3poZW5naGVpdGk,shadow_10,text_aHR0cHM6Ly9ibG9nLmNzZG4ubmV0L2NlbmNlcl9oZWFydA==,size_16,color_FFFFFF,t_70\" alt=\"在这里插入图片描述\"><br><img src=\"https://img-blog.csdnimg.cn/20210429233514469.png?x-oss-process=image/watermark,type_ZmFuZ3poZW5naGVpdGk,shadow_10,text_aHR0cHM6Ly9ibG9nLmNzZG4ubmV0L2NlbmNlcl9oZWFydA==,size_16,color_FFFFFF,t_70\" alt=\"在这里插入图片描述\"></p>\n<p><img src=\"https://img-blog.csdnimg.cn/20210429234709614.png?x-oss-process=image/watermark,type_ZmFuZ3poZW5naGVpdGk,shadow_10,text_aHR0cHM6Ly9ibG9nLmNzZG4ubmV0L2NlbmNlcl9oZWFydA==,size_16,color_FFFFFF,t_70\" alt=\"在这里插入图片描述\"></p>\n<h1 id=\"基础指令\"><a href=\"#基础指令\" class=\"headerlink\" title=\"基础指令\"></a>基础指令</h1><p>指令格式<br><code>指令体 参数 位置</code> </p>\n<h2 id=\"1、ls——列出\"><a href=\"#1、ls——列出\" class=\"headerlink\" title=\"1、ls——列出\"></a>1、ls——列出</h2><p>路径：</p>\n<blockquote><span class=\"custom-blockquote-svg\"><svg width=\"24\" height=\"24\" viewBox=\"0 0 24 24\" fill=\"\" xmlns=\"http://www.w3.org/2000/svg\" data-reactroot=\"\">\n<path fill=\"\" d=\"M22 12C22 6.5 17.5 2 12 2C6.5 2 2 6.5 2 12C2 17.5 6.5 22 12 22C13.8 22 15.5 21.5 17 20.6L22 22L20.7 17C21.5 15.5 22 13.8 22 12Z\" undefined=\"1\"></path>\n<path fill=\"\" d=\"M15.97 11.5H16.04C17.12 11.5 18 12.38 18 13.47V13.53C18 14.62 17.12 15.5 16.03 15.5H15.96C14.88 15.5 14 14.62 14 13.53V13.46C14 12.38 14.88 11.5 15.97 11.5Z\" undefined=\"1\"></path>\n<path fill=\"\" d=\"M7.97 11.5H8.04C9.12 11.5 10 12.38 10 13.47V13.53C10 14.62 9.12 15.5 8.03 15.5H7.97C6.88 15.5 6 14.62 6 13.53V13.46C6 12.38 6.88 11.5 7.97 11.5Z\" undefined=\"1\"></path>\n<path stroke-linejoin=\"round\" stroke-linecap=\"round\" stroke-miterlimit=\"10\" stroke-width=\"2\" stroke=\"\" d=\"M17 8.5C15.23 8.97 14.07 10.84 14.01 13.27C14 13.33 14 13.4 14 13.47V13.5\"></path>\n<path stroke-linejoin=\"round\" stroke-linecap=\"round\" stroke-miterlimit=\"10\" stroke-width=\"2\" stroke=\"\" d=\"M9 8.5C7.23 8.97 6.07 10.84 6.01 13.27C6 13.33 6 13.4 6 13.47V13.5\"></path>\n<path stroke-linejoin=\"round\" stroke-linecap=\"round\" stroke-miterlimit=\"10\" stroke-width=\"2\" stroke=\"\" d=\"M15.97 11.5H16.04C17.12 11.5 18 12.38 18 13.47V13.53C18 14.62 17.12 15.5 16.03 15.5H15.96C14.88 15.5 14 14.62 14 13.53V13.46C14 12.38 14.88 11.5 15.97 11.5Z\"></path>\n<path stroke-linejoin=\"round\" stroke-linecap=\"round\" stroke-miterlimit=\"10\" stroke-width=\"2\" stroke=\"\" d=\"M7.97 11.5H8.04C9.12 11.5 10 12.38 10 13.47V13.53C10 14.62 9.12 15.5 8.03 15.5H7.97C6.88 15.5 6 14.62 6 13.53V13.46C6 12.38 6.88 11.5 7.97 11.5Z\"></path>\n</svg>\n</span><p>相对路径：有一个参照物——当前工作目录，**..&#x2F;<strong>代表返回上级目录，</strong>.&#x2F;<strong>代表当前目录<br>绝对路径：以</strong>&#x2F;**开头的写法</p></blockquote>\n<p>参数</p>\n<ul>\n<li><p>a：all<br>列出所有，包括隐藏文件（以**.**开头的文件）<br>各列属性解析</p>\n</li>\n<li><p>l：list</p>\n</li>\n<li><p>h：以可读性较高的格式（主要是占用大小来展示）<br>问题：为什么很多文件都是4k？<br><img src=\"https://img-blog.csdnimg.cn/20210501131352954.png?x-oss-process=image/watermark,type_ZmFuZ3poZW5naGVpdGk,shadow_10,text_aHR0cHM6Ly9ibG9nLmNzZG4ubmV0L2NlbmNlcl9oZWFydA==,size_16,color_FFFFFF,t_70\" alt=\"在这里插入图片描述\"><br>A：文件夹本身占用4k大小，而不代表文件夹内容占用4K大小。（更加本质的原因是什么？我才和指针有关）</p>\n</li>\n</ul>\n<pre class=\"line-numbers language-none\"><code class=\"language-none\"><span aria-hidden=\"true\" class=\"line-numbers-rows\"><span></span></span></code></pre>\n<h2 id=\"2、pwd——打印当前目录\"><a href=\"#2、pwd——打印当前目录\" class=\"headerlink\" title=\"2、pwd——打印当前目录\"></a>2、pwd——打印当前目录</h2><h2 id=\"3、cd——切换工作目录\"><a href=\"#3、cd——切换工作目录\" class=\"headerlink\" title=\"3、cd——切换工作目录\"></a>3、cd——切换工作目录</h2><p><img src=\"https://img-blog.csdnimg.cn/20210501132302478.png\" alt=\"在这里插入图片描述\"></p>\n<h2 id=\"4、mkdir——创建目录\"><a href=\"#4、mkdir——创建目录\" class=\"headerlink\" title=\"4、mkdir——创建目录\"></a>4、mkdir——创建目录</h2><h3 id=\"mkdir-路径\"><a href=\"#mkdir-路径\" class=\"headerlink\" title=\"mkdir 路径\"></a>mkdir 路径</h3><p><img src=\"https://img-blog.csdnimg.cn/20210501132614471.png\" alt=\"在这里插入图片描述\"></p>\n<p>所有权限：可读可写可执行</p>\n<h3 id=\"mkdir-p-路径\"><a href=\"#mkdir-p-路径\" class=\"headerlink\" title=\"mkdir -p 路径\"></a>mkdir -p 路径</h3><p>-p：创建多级目录</p>\n<p>&#96;mkdir -p &#x2F;root&#x2F;a&#x2F;b&#x2F;c&#x2F;d’<br>abcd开始都不存在，如果不加-p不得行</p>\n<h3 id=\"mkdir-路径1-路径2-路径3\"><a href=\"#mkdir-路径1-路径2-路径3\" class=\"headerlink\" title=\"mkdir 路径1 路径2 路径3\"></a>mkdir 路径1 路径2 路径3</h3><p>一次性创建多个目录</p>\n<h2 id=\"5、touch——创建文件\"><a href=\"#5、touch——创建文件\" class=\"headerlink\" title=\"5、touch——创建文件\"></a>5、touch——创建文件</h2><h3 id=\"touch-文件名-后缀\"><a href=\"#touch-文件名-后缀\" class=\"headerlink\" title=\"touch 文件名.后缀\"></a>touch 文件名.后缀</h3><p>在当前工作目录下创建文件</p>\n<h3 id=\"touch-目录\"><a href=\"#touch-目录\" class=\"headerlink\" title=\"touch 目录\"></a>touch 目录</h3><h3 id=\"touch-文件1-文件2\"><a href=\"#touch-文件1-文件2\" class=\"headerlink\" title=\"touch 文件1 文件2\"></a>touch 文件1 文件2</h3><p>创建多个文件</p>\n<h2 id=\"6、cp——复制指令\"><a href=\"#6、cp——复制指令\" class=\"headerlink\" title=\"6、cp——复制指令\"></a>6、cp——复制指令</h2><p>copy</p>\n<h3 id=\"cp-被复制的文档路径-x2F-文件名-文档复制到的路径-x2F-文件名\"><a href=\"#cp-被复制的文档路径-x2F-文件名-文档复制到的路径-x2F-文件名\" class=\"headerlink\" title=\"cp 被复制的文档路径&#x2F;文件名 文档复制到的路径&#x2F;[文件名]\"></a>cp 被复制的文档路径&#x2F;文件名 文档复制到的路径&#x2F;[文件名]</h3><p>注两个文件名可以不一样，相当于复制完了再执行重命名操作，但是一般不这么做<br>第二个的文件名可选</p>\n<h3 id=\"cp-r-被复制的文件夹路径-复制到的文件夹路径\"><a href=\"#cp-r-被复制的文件夹路径-复制到的文件夹路径\" class=\"headerlink\" title=\"cp -r 被复制的文件夹路径 复制到的文件夹路径\"></a>cp -r 被复制的文件夹路径 复制到的文件夹路径</h3><p>-r表示递归，不只要拿文件夹还要文件夹下的文件和文件夹。<br><img src=\"https://img-blog.csdnimg.cn/20210501134205335.png\" alt=\"在这里插入图片描述\"><img src=\"https://img-blog.csdnimg.cn/20210501134219973.png\" alt=\"在这里插入图片描述\"><br><img src=\"https://img-blog.csdnimg.cn/20210501134255393.png\" alt=\"在这里插入图片描述\"></p>\n<p><img src=\"https://img-blog.csdnimg.cn/20210501134338134.png\" alt=\"在这里插入图片描述\"></p>\n<h2 id=\"7、mv——移动文件到新的位置\"><a href=\"#7、mv——移动文件到新的位置\" class=\"headerlink\" title=\"7、mv——移动文件到新的位置\"></a>7、mv——移动文件到新的位置</h2><p>move 移动</p>\n<h3 id=\"mv-需要移动的文档路径-x2F-文件名-移动到的文件路径-x2F-文件名\"><a href=\"#mv-需要移动的文档路径-x2F-文件名-移动到的文件路径-x2F-文件名\" class=\"headerlink\" title=\"mv 需要移动的文档路径&#x2F;文件名 移动到的文件路径&#x2F;[文件名]\"></a>mv 需要移动的文档路径&#x2F;文件名 移动到的文件路径&#x2F;[文件名]</h3><p><img src=\"https://img-blog.csdnimg.cn/20210501135108849.png?x-oss-process=image/watermark,type_ZmFuZ3poZW5naGVpdGk,shadow_10,text_aHR0cHM6Ly9ibG9nLmNzZG4ubmV0L2NlbmNlcl9oZWFydA==,size_16,color_FFFFFF,t_70\" alt=\"在这里插入图片描述\"></p>\n<h3 id=\"mv-需要移动的文件夹-需要移动到的地方\"><a href=\"#mv-需要移动的文件夹-需要移动到的地方\" class=\"headerlink\" title=\"mv 需要移动的文件夹 需要移动到的地方\"></a>mv 需要移动的文件夹 需要移动到的地方</h3><p>mv &#x2F;linuxcopy&#x2F;<br>py后面的&#x2F;可写可不写</p>\n<p><img src=\"https://img-blog.csdnimg.cn/20210501135341509.png\" alt=\"在这里插入图片描述\"></p>\n<h3 id=\"重命名\"><a href=\"#重命名\" class=\"headerlink\" title=\"重命名\"></a>重命名</h3><p><img src=\"https://img-blog.csdnimg.cn/20210501135427701.png\" alt=\"在这里插入图片描述\"><br><img src=\"https://img-blog.csdnimg.cn/20210501135624348.png\" alt=\"在这里插入图片描述\"></p>\n<h2 id=\"8、rm——删除指令\"><a href=\"#8、rm——删除指令\" class=\"headerlink\" title=\"8、rm——删除指令\"></a>8、rm——删除指令</h2><p>remove<br>rm -选项 文件<br>选项：</p>\n<ul>\n<li>-f</li>\n<li>-r</li>\n</ul>\n<p><img src=\"https://img-blog.csdnimg.cn/20210501140025649.png\" alt=\"在这里插入图片描述\"><br>双击tab可以预览有哪些符合条件的，再继续写</p>\n<h3 id=\"rm-f-文件\"><a href=\"#rm-f-文件\" class=\"headerlink\" title=\"rm -f 文件\"></a>rm -f 文件</h3><p><img src=\"https://img-blog.csdnimg.cn/20210501140707569.png\" alt=\"在这里插入图片描述\"></p>\n<h3 id=\"rm-rf-文件夹\"><a href=\"#rm-rf-文件夹\" class=\"headerlink\" title=\"rm -rf 文件夹\"></a>rm -rf 文件夹</h3><p><img src=\"https://img-blog.csdnimg.cn/20210501140640651.png\" alt=\"在这里插入图片描述\"><br><img src=\"https://img-blog.csdnimg.cn/20210501140652235.png\" alt=\"在这里插入图片描述\"></p>\n<h3 id=\"rm-rf-文件-文件夹\"><a href=\"#rm-rf-文件-文件夹\" class=\"headerlink\" title=\"rm -rf 文件 文件夹\"></a>rm -rf 文件 文件夹</h3><p><img src=\"https://img-blog.csdnimg.cn/20210501140554382.png\" alt=\"在这里插入图片描述\"></p>\n<h3 id=\"删除所有以linux开头的文件\"><a href=\"#删除所有以linux开头的文件\" class=\"headerlink\" title=\"删除所有以linux开头的文件\"></a>删除所有以linux开头的文件</h3><p>rm -rf linux*<br>*不管是什么，前面一样就行。通配符<br><img src=\"https://img-blog.csdnimg.cn/20210501140920129.png\" alt=\"在这里插入图片描述\"><br><img src=\"https://img-blog.csdnimg.cn/20210501140927740.png\" alt=\"在这里插入图片描述\"></p>\n<h2 id=\"9、vim\"><a href=\"#9、vim\" class=\"headerlink\" title=\"9、vim\"></a>9、vim</h2><p>vim是一款文本编辑器</p>\n<h3 id=\"vim-文件的路径\"><a href=\"#vim-文件的路径\" class=\"headerlink\" title=\"vim 文件的路径\"></a>vim 文件的路径</h3><p>打开一个文件（可以不存在，可以存在）</p>\n<h2 id=\"10、输出重定向\"><a href=\"#10、输出重定向\" class=\"headerlink\" title=\"10、输出重定向\"></a>10、输出重定向</h2><p>比如说ls有输出，一般都会显示到终端中，有时需要将命令结果保存到文件中进行分析统计，需要使用输出重定向</p>\n<ul>\n<li>&gt;：覆盖输出</li>\n<li>&gt;&gt;：追加输出<blockquote><span class=\"custom-blockquote-svg\"><svg width=\"24\" height=\"24\" viewBox=\"0 0 24 24\" fill=\"\" xmlns=\"http://www.w3.org/2000/svg\" data-reactroot=\"\">\n<path fill=\"\" d=\"M22 12C22 6.5 17.5 2 12 2C6.5 2 2 6.5 2 12C2 17.5 6.5 22 12 22C13.8 22 15.5 21.5 17 20.6L22 22L20.7 17C21.5 15.5 22 13.8 22 12Z\" undefined=\"1\"></path>\n<path fill=\"\" d=\"M15.97 11.5H16.04C17.12 11.5 18 12.38 18 13.47V13.53C18 14.62 17.12 15.5 16.03 15.5H15.96C14.88 15.5 14 14.62 14 13.53V13.46C14 12.38 14.88 11.5 15.97 11.5Z\" undefined=\"1\"></path>\n<path fill=\"\" d=\"M7.97 11.5H8.04C9.12 11.5 10 12.38 10 13.47V13.53C10 14.62 9.12 15.5 8.03 15.5H7.97C6.88 15.5 6 14.62 6 13.53V13.46C6 12.38 6.88 11.5 7.97 11.5Z\" undefined=\"1\"></path>\n<path stroke-linejoin=\"round\" stroke-linecap=\"round\" stroke-miterlimit=\"10\" stroke-width=\"2\" stroke=\"\" d=\"M17 8.5C15.23 8.97 14.07 10.84 14.01 13.27C14 13.33 14 13.4 14 13.47V13.5\"></path>\n<path stroke-linejoin=\"round\" stroke-linecap=\"round\" stroke-miterlimit=\"10\" stroke-width=\"2\" stroke=\"\" d=\"M9 8.5C7.23 8.97 6.07 10.84 6.01 13.27C6 13.33 6 13.4 6 13.47V13.5\"></path>\n<path stroke-linejoin=\"round\" stroke-linecap=\"round\" stroke-miterlimit=\"10\" stroke-width=\"2\" stroke=\"\" d=\"M15.97 11.5H16.04C17.12 11.5 18 12.38 18 13.47V13.53C18 14.62 17.12 15.5 16.03 15.5H15.96C14.88 15.5 14 14.62 14 13.53V13.46C14 12.38 14.88 11.5 15.97 11.5Z\"></path>\n<path stroke-linejoin=\"round\" stroke-linecap=\"round\" stroke-miterlimit=\"10\" stroke-width=\"2\" stroke=\"\" d=\"M7.97 11.5H8.04C9.12 11.5 10 12.38 10 13.47V13.53C10 14.62 9.12 15.5 8.03 15.5H7.97C6.88 15.5 6 14.62 6 13.53V13.46C6 12.38 6.88 11.5 7.97 11.5Z\"></path>\n</svg>\n</span><p>csdn中”&gt;”不能直接输入而是输入<code>&amp;gt;</code>，同理”&lt;”用<code>&amp;lt;</code><br><code>ls -al &gt; ls.txt</code></p></blockquote>\n</li>\n</ul>\n<p>创建了新文件ls.txt，如果有的</p>\n<h2 id=\"cat\"><a href=\"#cat\" class=\"headerlink\" title=\"cat\"></a>cat</h2><p>作用1：cat有<strong>直接打开</strong>一个文件的功能 ，类似于预览</p>\n<h3 id=\"cat-文件路径\"><a href=\"#cat-文件路径\" class=\"headerlink\" title=\"cat 文件路径\"></a>cat 文件路径</h3><h3 id=\"cat-还可以对文件进行合并\"><a href=\"#cat-还可以对文件进行合并\" class=\"headerlink\" title=\"cat 还可以对文件进行合并\"></a>cat 还可以对文件进行合并</h3><p>cat 待合并的文件路径1 待合并的文件路径2 &gt; 合并之后的文件路径</p>\n<h1 id=\"进阶指令\"><a href=\"#进阶指令\" class=\"headerlink\" title=\"进阶指令\"></a>进阶指令</h1><h2 id=\"1、df指令——查看磁盘空间\"><a href=\"#1、df指令——查看磁盘空间\" class=\"headerlink\" title=\"1、df指令——查看磁盘空间\"></a>1、df指令——查看磁盘空间</h2><p>作用：查看磁盘空间<br><img src=\"https://img-blog.csdnimg.cn/2021050118202230.png?x-oss-process=image/watermark,type_ZmFuZ3poZW5naGVpdGk,shadow_10,text_aHR0cHM6Ly9ibG9nLmNzZG4ubmV0L2NlbmNlcl9oZWFydA==,size_16,color_FFFFFF,t_70\" alt=\"在这里插入图片描述\"><br>经常用<code>df -h</code></p>\n<p>monted on挂载点——分配盘符</p>\n<h2 id=\"2、free-指令——查看内存使用情况\"><a href=\"#2、free-指令——查看内存使用情况\" class=\"headerlink\" title=\"2、free 指令——查看内存使用情况\"></a>2、free 指令——查看内存使用情况</h2><p>语法：free [-m]<br>-m：Mb<br><img src=\"https://img-blog.csdnimg.cn/20210501182708183.png\" alt=\"在这里插入图片描述\"></p>\n<p><img src=\"https://img-blog.csdnimg.cn/20210501183324437.png\" alt=\"在这里插入图片描述\"></p>\n<h2 id=\"3、head——查看前n行\"><a href=\"#3、head——查看前n行\" class=\"headerlink\" title=\"3、head——查看前n行\"></a>3、head——查看前n行</h2><p>查看一个文件的前n行，如果不指定n，则默认前10行<br>也是一种预览，和cat类似但是cat会全部弄出来<br><code>head -n 文件路径</code></p>\n<h2 id=\"4、tail——查看后n行\"><a href=\"#4、tail——查看后n行\" class=\"headerlink\" title=\"4、tail——查看后n行\"></a>4、tail——查看后n行</h2><p>查看一个文件的后n行，如果不指定n，则默认后10行</p>\n<h3 id=\"tail-n-文件路径\"><a href=\"#tail-n-文件路径\" class=\"headerlink\" title=\"tail-n 文件路径\"></a>tail-n 文件路径</h3><h3 id=\"tail-f-文件路径\"><a href=\"#tail-f-文件路径\" class=\"headerlink\" title=\"tail -f 文件路径\"></a>tail -f 文件路径</h3><p>作用：可以通过tail来查看文件的动态变化，变化的内容不能是用户手动增加的<br>退出按q即可</p>\n<h2 id=\"5、less——查看文件\"><a href=\"#5、less——查看文件\" class=\"headerlink\" title=\"5、less——查看文件\"></a>5、less——查看文件</h2><p>以较少内容进行输出，按下辅助功能键查看更多<br>语法：less 需要查看的文件路径</p>\n<p>空格，一页一页的翻<br>数字+回车<br>上下方向键</p>\n<h2 id=\"6、wc——统计文件内容信息\"><a href=\"#6、wc——统计文件内容信息\" class=\"headerlink\" title=\"6、wc——统计文件内容信息\"></a>6、wc——统计文件内容信息</h2><p>信息：行数，单词数，字节数<br><img src=\"https://img-blog.csdnimg.cn/20210501184911232.png\" alt=\"在这里插入图片描述\"><br>语法：wc -lwc 需要统计的文件路径</p>\n<ul>\n<li>l：lines：行数</li>\n<li>w：words，单词数</li>\n<li>c：byte，字节数<br>单词数：<blockquote><span class=\"custom-blockquote-svg\"><svg width=\"24\" height=\"24\" viewBox=\"0 0 24 24\" fill=\"\" xmlns=\"http://www.w3.org/2000/svg\" data-reactroot=\"\">\n<path fill=\"\" d=\"M22 12C22 6.5 17.5 2 12 2C6.5 2 2 6.5 2 12C2 17.5 6.5 22 12 22C13.8 22 15.5 21.5 17 20.6L22 22L20.7 17C21.5 15.5 22 13.8 22 12Z\" undefined=\"1\"></path>\n<path fill=\"\" d=\"M15.97 11.5H16.04C17.12 11.5 18 12.38 18 13.47V13.53C18 14.62 17.12 15.5 16.03 15.5H15.96C14.88 15.5 14 14.62 14 13.53V13.46C14 12.38 14.88 11.5 15.97 11.5Z\" undefined=\"1\"></path>\n<path fill=\"\" d=\"M7.97 11.5H8.04C9.12 11.5 10 12.38 10 13.47V13.53C10 14.62 9.12 15.5 8.03 15.5H7.97C6.88 15.5 6 14.62 6 13.53V13.46C6 12.38 6.88 11.5 7.97 11.5Z\" undefined=\"1\"></path>\n<path stroke-linejoin=\"round\" stroke-linecap=\"round\" stroke-miterlimit=\"10\" stroke-width=\"2\" stroke=\"\" d=\"M17 8.5C15.23 8.97 14.07 10.84 14.01 13.27C14 13.33 14 13.4 14 13.47V13.5\"></path>\n<path stroke-linejoin=\"round\" stroke-linecap=\"round\" stroke-miterlimit=\"10\" stroke-width=\"2\" stroke=\"\" d=\"M9 8.5C7.23 8.97 6.07 10.84 6.01 13.27C6 13.33 6 13.4 6 13.47V13.5\"></path>\n<path stroke-linejoin=\"round\" stroke-linecap=\"round\" stroke-miterlimit=\"10\" stroke-width=\"2\" stroke=\"\" d=\"M15.97 11.5H16.04C17.12 11.5 18 12.38 18 13.47V13.53C18 14.62 17.12 15.5 16.03 15.5H15.96C14.88 15.5 14 14.62 14 13.53V13.46C14 12.38 14.88 11.5 15.97 11.5Z\"></path>\n<path stroke-linejoin=\"round\" stroke-linecap=\"round\" stroke-miterlimit=\"10\" stroke-width=\"2\" stroke=\"\" d=\"M7.97 11.5H8.04C9.12 11.5 10 12.38 10 13.47V13.53C10 14.62 9.12 15.5 8.03 15.5H7.97C6.88 15.5 6 14.62 6 13.53V13.46C6 12.38 6.88 11.5 7.97 11.5Z\"></path>\n</svg>\n</span><p>依靠空格来判断单词数量，中 国 （三个单词）</p></blockquote>\n<h2 id=\"date指令（重点）——表示操作时间日期\"><a href=\"#date指令（重点）——表示操作时间日期\" class=\"headerlink\" title=\"date指令（重点）——表示操作时间日期\"></a>date指令（重点）——表示操作时间日期</h2><p>操作：读取，设置（后面shell脚本需要用）</p>\n</li>\n</ul>\n<p>+号表示读取</p>\n<h3 id=\"date\"><a href=\"#date\" class=\"headerlink\" title=\"date\"></a>date</h3><p>输出当前时间<br><img src=\"https://img-blog.csdnimg.cn/20210501185808380.png\" alt=\"在这里插入图片描述\"></p>\n<ul>\n<li>CST：当地时间</li>\n<li>UCT：</li>\n<li>GMT</li>\n</ul>\n<h3 id=\"date-F\"><a href=\"#date-F\" class=\"headerlink\" title=\"date +%F\"></a>date +%F</h3><p>输出年月日必须大写<br><img src=\"https://img-blog.csdnimg.cn/2021050119001638.png\" alt=\"在这里插入图片描述\"></p>\n<p>复杂写法：<code>date &quot;+%Y-%m-%d&quot;</code></p>\n<p>大小写不一样</p>\n<h3 id=\"date-“-F-T”\"><a href=\"#date-“-F-T”\" class=\"headerlink\" title=\"date “+%F %T”\"></a>date “+%F %T”</h3><p><img src=\"https://img-blog.csdnimg.cn/20210501190337658.png\" alt=\"在这里插入图片描述\"><br>为什么要有””呢，因为要把后面的当做一个整体</p>\n<p>等价于：<code>date &quot;+%Y-%m-%d  %H:%M:%S&quot;</code><br><img src=\"https://img-blog.csdnimg.cn/20210501190611207.png\" alt=\"在这里插入图片描述\"></p>\n<h2 id=\"\"><a href=\"#\" class=\"headerlink\" title=\"\"></a></h2><p>符号可选：+之后，-之前<br>单位可选：day，mouth，year</p>\n<p><img src=\"https://img-blog.csdnimg.cn/20210501190906366.png\" alt=\"在这里插入图片描述\"></p>\n<h2 id=\"8、cal——操作日历\"><a href=\"#8、cal——操作日历\" class=\"headerlink\" title=\"8、cal——操作日历\"></a>8、cal——操作日历</h2><h3 id=\"cal\"><a href=\"#cal\" class=\"headerlink\" title=\"cal\"></a>cal</h3><p>直接输出当前月份的日历</p>\n<h2 id=\"9、clear-x2F-ctrl-L\"><a href=\"#9、clear-x2F-ctrl-L\" class=\"headerlink\" title=\"9、clear&#x2F;ctrl+L\"></a>9、clear&#x2F;ctrl+L</h2><p>作用：清除终端中已经存在的命令和结果<br><img src=\"https://img-blog.csdnimg.cn/20210502110246485.png\" alt=\"在这里插入图片描述\"></p>\n<h2 id=\"10、管道\"><a href=\"#10、管道\" class=\"headerlink\" title=\"10、管道\"></a>10、管道</h2><p>管道符：<code>|</code>不是1或者小写的l<br>作用：</p>\n<ul>\n<li>☆过滤</li>\n<li>特殊</li>\n<li>扩展处理<br>不能单独使用，必须需要配合前面所讲的一些指令一起使用，作用是为了辅助作用</li>\n</ul>\n<h3 id=\"过滤，类似于正则\"><a href=\"#过滤，类似于正则\" class=\"headerlink\" title=\"过滤，类似于正则\"></a>过滤，类似于正则</h3><p>需要通过管道查询出根目录下包含“b”字母的文档名称<br><code>ls /|grep b</code><br><img src=\"https://img-blog.csdnimg.cn/2021050211090936.png\" alt=\"在这里插入图片描述\"><br>Linux grep 命令用于查找文件里符合条件的字符串</p>\n<p><img src=\"https://img-blog.csdnimg.cn/20210502111127997.png\" alt=\"在这里插入图片描述\"></p>\n<h3 id=\"ls-x2F-wc-l\"><a href=\"#ls-x2F-wc-l\" class=\"headerlink\" title=\"ls &#x2F; | wc -l\"></a>ls &#x2F; | wc -l</h3><p>查看&#x2F;下有多少个文件</p>\n<h1 id=\"高级指令\"><a href=\"#高级指令\" class=\"headerlink\" title=\"高级指令\"></a>高级指令</h1><h2 id=\"hostname\"><a href=\"#hostname\" class=\"headerlink\" title=\"hostname\"></a>hostname</h2><p>host主机<br>name名字<br>操作服务器的主机名（读取，设置）<br>这个设置是一次性的，是后面基本不用的<br>只是掌握读取就行</p>\n<p>为什么要操作它： </p>\n<h3 id=\"hostname-1\"><a href=\"#hostname-1\" class=\"headerlink\" title=\"hostname\"></a>hostname</h3><p><img src=\"https://img-blog.csdnimg.cn/20210502112429961.png\" alt=\"在这里插入图片描述\"></p>\n<h3 id=\"hostname-f\"><a href=\"#hostname-f\" class=\"headerlink\" title=\"hostname -f\"></a>hostname -f</h3><p>输出当前主机名总得fqdn（全限定<strong>域名</strong>）</p>\n<p><img src=\"https://img-blog.csdnimg.cn/20210502112519132.png\" alt=\"在这里插入图片描述\"></p>\n<h2 id=\"id\"><a href=\"#id\" class=\"headerlink\" title=\"id\"></a>id</h2><h3 id=\"-1\"><a href=\"#-1\" class=\"headerlink\" title=\"\"></a></h3><h2 id=\"whoami\"><a href=\"#whoami\" class=\"headerlink\" title=\"whoami\"></a>whoami</h2><p><img src=\"https://img-blog.csdnimg.cn/2021050218441741.png\" alt=\"在这里插入图片描述\"><br>在脚本中使用<br>告诉程序自己是谁，日志shell脚本</p>\n<h2 id=\"☆ps-ef\"><a href=\"#☆ps-ef\" class=\"headerlink\" title=\"☆ps -ef\"></a>☆ps -ef</h2><p>ps 查看服务器的进程信息</p>\n<p><img src=\"https://img-blog.csdnimg.cn/20210502185219961.png\" alt=\"在这里插入图片描述\"><br><img src=\"https://img-blog.csdnimg.cn/20210502185411618.png\" alt=\"在这里插入图片描述\"></p>\n<p><img src=\"https://img-blog.csdnimg.cn/20210502185642661.png?x-oss-process=image/watermark,type_ZmFuZ3poZW5naGVpdGk,shadow_10,text_aHR0cHM6Ly9ibG9nLmNzZG4ubmV0L2NlbmNlcl9oZWFydA==,size_16,color_FFFFFF,t_70\" alt=\"在这里插入图片描述\"><br>ps结果中过滤出想要查看的进程状态<br><code>ps -ef | gerp 进程名称</code></p>\n<h2 id=\"top\"><a href=\"#top\" class=\"headerlink\" title=\"top\"></a>top</h2><p>查看服务器的进程站的资源<br><img src=\"https://img-blog.csdnimg.cn/20210502190307766.png?x-oss-process=image/watermark,type_ZmFuZ3poZW5naGVpdGk,shadow_10,text_aHR0cHM6Ly9ibG9nLmNzZG4ubmV0L2NlbmNlcl9oZWFydA==,size_16,color_FFFFFF,t_70\" alt=\"在这里插入图片描述\"><br>退出按q</p>\n<h1 id=\"vi和vim编辑器\"><a href=\"#vi和vim编辑器\" class=\"headerlink\" title=\"vi和vim编辑器\"></a>vi和vim编辑器</h1><h2 id=\"6-1-vi和vim的基本介绍\"><a href=\"#6-1-vi和vim的基本介绍\" class=\"headerlink\" title=\"6.1 vi和vim的基本介绍\"></a>6.1 vi和vim的基本介绍</h2><p>vi是文本编辑器<br>vim是增强版的文本编辑器（加入了代码补充，高亮等等）</p>\n<h2 id=\"6-2-三种模式\"><a href=\"#6-2-三种模式\" class=\"headerlink\" title=\"6.2 三种模式\"></a>6.2 三种模式</h2><ul>\n<li>正常模式<br>用vim打开文件，就可以进入正常模式，在正常模式下可以使用快捷键</li>\n<li>插入模式&#x2F;编辑模式<br>该模式下，可以输入内容<br>按下i,I,o,O,a,A,r,R都可以进入，但有小的区别</li>\n<li>命令行模式<br>可以保存退出，可以输入一些命令，可以提供相关指令，完成读取，存盘，替换，离开等等</li>\n</ul>\n<p><img src=\"https://img-blog.csdnimg.cn/8ffdad62c83f447aaa660a40d10b9d9e.png?x-oss-process=image/watermark,type_d3F5LXplbmhlaQ,shadow_50,text_Q1NETiBAQ2VuY3Vz,size_20,color_FFFFFF,t_70,g_se,x_16\" alt=\"在这里插入图片描述\"></p>\n<h2 id=\"6-3-vi和vim的快捷键\"><a href=\"#6-3-vi和vim的快捷键\" class=\"headerlink\" title=\"6.3 vi和vim的快捷键\"></a>6.3 vi和vim的快捷键</h2><ol>\n<li>拷贝当前行<strong>yy</strong>，拷贝当前行向下的5行，并粘贴。p粘贴不用着急慢慢弄</li>\n<li>删除当前行dd,删除当前行向下的5行<strong>5dd</strong></li>\n<li>在文件中查找某个单词，【命令行 <strong>&#x2F;关键词</strong>，回车查找，输入<strong>n</strong>就是查找下一个】</li>\n<li>设置文件的行号，取消文件的行号（命令下**:set nu<strong>和</strong>:set nonu**）</li>\n<li>编辑 &#x2F;etc&#x2F;profile文件，使用快捷键到文档的最末行：<strong>G</strong>（<strong>shift+g</strong>）和最首行<strong>gg</strong>(正常模式下)，注意都是在正常模式下执行的</li>\n<li>在一个文件中输入hello，然后有撤销这个动作，在正常模式下输入<strong>u</strong></li>\n<li>编辑 &#x2F;etc&#x2F;profile文件，并将光标移动到第20行 shift+g<br>第一步显示行号：<code>:set nu</code><br>第二步：输入20<br>第三步：输入shift+g</li>\n</ol>\n<p>要么就是唯一映射，要么就是有操作栈，达成唯一条件就跳出</p>\n","text":" 基础指令指令格式指令体 参数 位置 1、ls——列出路径： 相对路径：有一个参照物——当前工作目录，**..&#x2F;代表返回上级目录，.&#x2F;代表当前目录绝对路径：以&#x2F;**开头的写法 参数 a：all列出所有，包括隐藏文件（以**.**开头的文件）各列属性解...","link":"","photos":[],"count_time":{"symbolsCount":"3k","symbolsTime":"3 mins."},"categories":[],"tags":[{"name":"大数据","slug":"大数据","count":3,"path":"api/tags/大数据.json"}],"toc":"<ol class=\"toc\"><li class=\"toc-item toc-level-1\"><a class=\"toc-link\" href=\"#%E5%9F%BA%E7%A1%80%E6%8C%87%E4%BB%A4\"><span class=\"toc-text\">基础指令</span></a><ol class=\"toc-child\"><li class=\"toc-item toc-level-2\"><a class=\"toc-link\" href=\"#1%E3%80%81ls%E2%80%94%E2%80%94%E5%88%97%E5%87%BA\"><span class=\"toc-text\">1、ls——列出</span></a></li><li class=\"toc-item toc-level-2\"><a class=\"toc-link\" href=\"#2%E3%80%81pwd%E2%80%94%E2%80%94%E6%89%93%E5%8D%B0%E5%BD%93%E5%89%8D%E7%9B%AE%E5%BD%95\"><span class=\"toc-text\">2、pwd——打印当前目录</span></a></li><li class=\"toc-item toc-level-2\"><a class=\"toc-link\" href=\"#3%E3%80%81cd%E2%80%94%E2%80%94%E5%88%87%E6%8D%A2%E5%B7%A5%E4%BD%9C%E7%9B%AE%E5%BD%95\"><span class=\"toc-text\">3、cd——切换工作目录</span></a></li><li class=\"toc-item toc-level-2\"><a class=\"toc-link\" href=\"#4%E3%80%81mkdir%E2%80%94%E2%80%94%E5%88%9B%E5%BB%BA%E7%9B%AE%E5%BD%95\"><span class=\"toc-text\">4、mkdir——创建目录</span></a><ol class=\"toc-child\"><li class=\"toc-item toc-level-3\"><a class=\"toc-link\" href=\"#mkdir-%E8%B7%AF%E5%BE%84\"><span class=\"toc-text\">mkdir 路径</span></a></li><li class=\"toc-item toc-level-3\"><a class=\"toc-link\" href=\"#mkdir-p-%E8%B7%AF%E5%BE%84\"><span class=\"toc-text\">mkdir -p 路径</span></a></li><li class=\"toc-item toc-level-3\"><a class=\"toc-link\" href=\"#mkdir-%E8%B7%AF%E5%BE%841-%E8%B7%AF%E5%BE%842-%E8%B7%AF%E5%BE%843\"><span class=\"toc-text\">mkdir 路径1 路径2 路径3</span></a></li></ol></li><li class=\"toc-item toc-level-2\"><a class=\"toc-link\" href=\"#5%E3%80%81touch%E2%80%94%E2%80%94%E5%88%9B%E5%BB%BA%E6%96%87%E4%BB%B6\"><span class=\"toc-text\">5、touch——创建文件</span></a><ol class=\"toc-child\"><li class=\"toc-item toc-level-3\"><a class=\"toc-link\" href=\"#touch-%E6%96%87%E4%BB%B6%E5%90%8D-%E5%90%8E%E7%BC%80\"><span class=\"toc-text\">touch 文件名.后缀</span></a></li><li class=\"toc-item toc-level-3\"><a class=\"toc-link\" href=\"#touch-%E7%9B%AE%E5%BD%95\"><span class=\"toc-text\">touch 目录</span></a></li><li class=\"toc-item toc-level-3\"><a class=\"toc-link\" href=\"#touch-%E6%96%87%E4%BB%B61-%E6%96%87%E4%BB%B62\"><span class=\"toc-text\">touch 文件1 文件2</span></a></li></ol></li><li class=\"toc-item toc-level-2\"><a class=\"toc-link\" href=\"#6%E3%80%81cp%E2%80%94%E2%80%94%E5%A4%8D%E5%88%B6%E6%8C%87%E4%BB%A4\"><span class=\"toc-text\">6、cp——复制指令</span></a><ol class=\"toc-child\"><li class=\"toc-item toc-level-3\"><a class=\"toc-link\" href=\"#cp-%E8%A2%AB%E5%A4%8D%E5%88%B6%E7%9A%84%E6%96%87%E6%A1%A3%E8%B7%AF%E5%BE%84-x2F-%E6%96%87%E4%BB%B6%E5%90%8D-%E6%96%87%E6%A1%A3%E5%A4%8D%E5%88%B6%E5%88%B0%E7%9A%84%E8%B7%AF%E5%BE%84-x2F-%E6%96%87%E4%BB%B6%E5%90%8D\"><span class=\"toc-text\">cp 被复制的文档路径&#x2F;文件名 文档复制到的路径&#x2F;[文件名]</span></a></li><li class=\"toc-item toc-level-3\"><a class=\"toc-link\" href=\"#cp-r-%E8%A2%AB%E5%A4%8D%E5%88%B6%E7%9A%84%E6%96%87%E4%BB%B6%E5%A4%B9%E8%B7%AF%E5%BE%84-%E5%A4%8D%E5%88%B6%E5%88%B0%E7%9A%84%E6%96%87%E4%BB%B6%E5%A4%B9%E8%B7%AF%E5%BE%84\"><span class=\"toc-text\">cp -r 被复制的文件夹路径 复制到的文件夹路径</span></a></li></ol></li><li class=\"toc-item toc-level-2\"><a class=\"toc-link\" href=\"#7%E3%80%81mv%E2%80%94%E2%80%94%E7%A7%BB%E5%8A%A8%E6%96%87%E4%BB%B6%E5%88%B0%E6%96%B0%E7%9A%84%E4%BD%8D%E7%BD%AE\"><span class=\"toc-text\">7、mv——移动文件到新的位置</span></a><ol class=\"toc-child\"><li class=\"toc-item toc-level-3\"><a class=\"toc-link\" href=\"#mv-%E9%9C%80%E8%A6%81%E7%A7%BB%E5%8A%A8%E7%9A%84%E6%96%87%E6%A1%A3%E8%B7%AF%E5%BE%84-x2F-%E6%96%87%E4%BB%B6%E5%90%8D-%E7%A7%BB%E5%8A%A8%E5%88%B0%E7%9A%84%E6%96%87%E4%BB%B6%E8%B7%AF%E5%BE%84-x2F-%E6%96%87%E4%BB%B6%E5%90%8D\"><span class=\"toc-text\">mv 需要移动的文档路径&#x2F;文件名 移动到的文件路径&#x2F;[文件名]</span></a></li><li class=\"toc-item toc-level-3\"><a class=\"toc-link\" href=\"#mv-%E9%9C%80%E8%A6%81%E7%A7%BB%E5%8A%A8%E7%9A%84%E6%96%87%E4%BB%B6%E5%A4%B9-%E9%9C%80%E8%A6%81%E7%A7%BB%E5%8A%A8%E5%88%B0%E7%9A%84%E5%9C%B0%E6%96%B9\"><span class=\"toc-text\">mv 需要移动的文件夹 需要移动到的地方</span></a></li><li class=\"toc-item toc-level-3\"><a class=\"toc-link\" href=\"#%E9%87%8D%E5%91%BD%E5%90%8D\"><span class=\"toc-text\">重命名</span></a></li></ol></li><li class=\"toc-item toc-level-2\"><a class=\"toc-link\" href=\"#8%E3%80%81rm%E2%80%94%E2%80%94%E5%88%A0%E9%99%A4%E6%8C%87%E4%BB%A4\"><span class=\"toc-text\">8、rm——删除指令</span></a><ol class=\"toc-child\"><li class=\"toc-item toc-level-3\"><a class=\"toc-link\" href=\"#rm-f-%E6%96%87%E4%BB%B6\"><span class=\"toc-text\">rm -f 文件</span></a></li><li class=\"toc-item toc-level-3\"><a class=\"toc-link\" href=\"#rm-rf-%E6%96%87%E4%BB%B6%E5%A4%B9\"><span class=\"toc-text\">rm -rf 文件夹</span></a></li><li class=\"toc-item toc-level-3\"><a class=\"toc-link\" href=\"#rm-rf-%E6%96%87%E4%BB%B6-%E6%96%87%E4%BB%B6%E5%A4%B9\"><span class=\"toc-text\">rm -rf 文件 文件夹</span></a></li><li class=\"toc-item toc-level-3\"><a class=\"toc-link\" href=\"#%E5%88%A0%E9%99%A4%E6%89%80%E6%9C%89%E4%BB%A5linux%E5%BC%80%E5%A4%B4%E7%9A%84%E6%96%87%E4%BB%B6\"><span class=\"toc-text\">删除所有以linux开头的文件</span></a></li></ol></li><li class=\"toc-item toc-level-2\"><a class=\"toc-link\" href=\"#9%E3%80%81vim\"><span class=\"toc-text\">9、vim</span></a><ol class=\"toc-child\"><li class=\"toc-item toc-level-3\"><a class=\"toc-link\" href=\"#vim-%E6%96%87%E4%BB%B6%E7%9A%84%E8%B7%AF%E5%BE%84\"><span class=\"toc-text\">vim 文件的路径</span></a></li></ol></li><li class=\"toc-item toc-level-2\"><a class=\"toc-link\" href=\"#10%E3%80%81%E8%BE%93%E5%87%BA%E9%87%8D%E5%AE%9A%E5%90%91\"><span class=\"toc-text\">10、输出重定向</span></a></li><li class=\"toc-item toc-level-2\"><a class=\"toc-link\" href=\"#cat\"><span class=\"toc-text\">cat</span></a><ol class=\"toc-child\"><li class=\"toc-item toc-level-3\"><a class=\"toc-link\" href=\"#cat-%E6%96%87%E4%BB%B6%E8%B7%AF%E5%BE%84\"><span class=\"toc-text\">cat 文件路径</span></a></li><li class=\"toc-item toc-level-3\"><a class=\"toc-link\" href=\"#cat-%E8%BF%98%E5%8F%AF%E4%BB%A5%E5%AF%B9%E6%96%87%E4%BB%B6%E8%BF%9B%E8%A1%8C%E5%90%88%E5%B9%B6\"><span class=\"toc-text\">cat 还可以对文件进行合并</span></a></li></ol></li></ol></li><li class=\"toc-item toc-level-1\"><a class=\"toc-link\" href=\"#%E8%BF%9B%E9%98%B6%E6%8C%87%E4%BB%A4\"><span class=\"toc-text\">进阶指令</span></a><ol class=\"toc-child\"><li class=\"toc-item toc-level-2\"><a class=\"toc-link\" href=\"#1%E3%80%81df%E6%8C%87%E4%BB%A4%E2%80%94%E2%80%94%E6%9F%A5%E7%9C%8B%E7%A3%81%E7%9B%98%E7%A9%BA%E9%97%B4\"><span class=\"toc-text\">1、df指令——查看磁盘空间</span></a></li><li class=\"toc-item toc-level-2\"><a class=\"toc-link\" href=\"#2%E3%80%81free-%E6%8C%87%E4%BB%A4%E2%80%94%E2%80%94%E6%9F%A5%E7%9C%8B%E5%86%85%E5%AD%98%E4%BD%BF%E7%94%A8%E6%83%85%E5%86%B5\"><span class=\"toc-text\">2、free 指令——查看内存使用情况</span></a></li><li class=\"toc-item toc-level-2\"><a class=\"toc-link\" href=\"#3%E3%80%81head%E2%80%94%E2%80%94%E6%9F%A5%E7%9C%8B%E5%89%8Dn%E8%A1%8C\"><span class=\"toc-text\">3、head——查看前n行</span></a></li><li class=\"toc-item toc-level-2\"><a class=\"toc-link\" href=\"#4%E3%80%81tail%E2%80%94%E2%80%94%E6%9F%A5%E7%9C%8B%E5%90%8En%E8%A1%8C\"><span class=\"toc-text\">4、tail——查看后n行</span></a><ol class=\"toc-child\"><li class=\"toc-item toc-level-3\"><a class=\"toc-link\" href=\"#tail-n-%E6%96%87%E4%BB%B6%E8%B7%AF%E5%BE%84\"><span class=\"toc-text\">tail-n 文件路径</span></a></li><li class=\"toc-item toc-level-3\"><a class=\"toc-link\" href=\"#tail-f-%E6%96%87%E4%BB%B6%E8%B7%AF%E5%BE%84\"><span class=\"toc-text\">tail -f 文件路径</span></a></li></ol></li><li class=\"toc-item toc-level-2\"><a class=\"toc-link\" href=\"#5%E3%80%81less%E2%80%94%E2%80%94%E6%9F%A5%E7%9C%8B%E6%96%87%E4%BB%B6\"><span class=\"toc-text\">5、less——查看文件</span></a></li><li class=\"toc-item toc-level-2\"><a class=\"toc-link\" href=\"#6%E3%80%81wc%E2%80%94%E2%80%94%E7%BB%9F%E8%AE%A1%E6%96%87%E4%BB%B6%E5%86%85%E5%AE%B9%E4%BF%A1%E6%81%AF\"><span class=\"toc-text\">6、wc——统计文件内容信息</span></a></li><li class=\"toc-item toc-level-2\"><a class=\"toc-link\" href=\"#date%E6%8C%87%E4%BB%A4%EF%BC%88%E9%87%8D%E7%82%B9%EF%BC%89%E2%80%94%E2%80%94%E8%A1%A8%E7%A4%BA%E6%93%8D%E4%BD%9C%E6%97%B6%E9%97%B4%E6%97%A5%E6%9C%9F\"><span class=\"toc-text\">date指令（重点）——表示操作时间日期</span></a><ol class=\"toc-child\"><li class=\"toc-item toc-level-3\"><a class=\"toc-link\" href=\"#date\"><span class=\"toc-text\">date</span></a></li><li class=\"toc-item toc-level-3\"><a class=\"toc-link\" href=\"#date-F\"><span class=\"toc-text\">date +%F</span></a></li><li class=\"toc-item toc-level-3\"><a class=\"toc-link\" href=\"#date-%E2%80%9C-F-T%E2%80%9D\"><span class=\"toc-text\">date “+%F %T”</span></a></li></ol></li><li class=\"toc-item toc-level-2\"><a class=\"toc-link\"><span class=\"toc-text\"></span></a></li><li class=\"toc-item toc-level-2\"><a class=\"toc-link\" href=\"#8%E3%80%81cal%E2%80%94%E2%80%94%E6%93%8D%E4%BD%9C%E6%97%A5%E5%8E%86\"><span class=\"toc-text\">8、cal——操作日历</span></a><ol class=\"toc-child\"><li class=\"toc-item toc-level-3\"><a class=\"toc-link\" href=\"#cal\"><span class=\"toc-text\">cal</span></a></li></ol></li><li class=\"toc-item toc-level-2\"><a class=\"toc-link\" href=\"#9%E3%80%81clear-x2F-ctrl-L\"><span class=\"toc-text\">9、clear&#x2F;ctrl+L</span></a></li><li class=\"toc-item toc-level-2\"><a class=\"toc-link\" href=\"#10%E3%80%81%E7%AE%A1%E9%81%93\"><span class=\"toc-text\">10、管道</span></a><ol class=\"toc-child\"><li class=\"toc-item toc-level-3\"><a class=\"toc-link\" href=\"#%E8%BF%87%E6%BB%A4%EF%BC%8C%E7%B1%BB%E4%BC%BC%E4%BA%8E%E6%AD%A3%E5%88%99\"><span class=\"toc-text\">过滤，类似于正则</span></a></li><li class=\"toc-item toc-level-3\"><a class=\"toc-link\" href=\"#ls-x2F-wc-l\"><span class=\"toc-text\">ls &#x2F; | wc -l</span></a></li></ol></li></ol></li><li class=\"toc-item toc-level-1\"><a class=\"toc-link\" href=\"#%E9%AB%98%E7%BA%A7%E6%8C%87%E4%BB%A4\"><span class=\"toc-text\">高级指令</span></a><ol class=\"toc-child\"><li class=\"toc-item toc-level-2\"><a class=\"toc-link\" href=\"#hostname\"><span class=\"toc-text\">hostname</span></a><ol class=\"toc-child\"><li class=\"toc-item toc-level-3\"><a class=\"toc-link\" href=\"#hostname-1\"><span class=\"toc-text\">hostname</span></a></li><li class=\"toc-item toc-level-3\"><a class=\"toc-link\" href=\"#hostname-f\"><span class=\"toc-text\">hostname -f</span></a></li></ol></li><li class=\"toc-item toc-level-2\"><a class=\"toc-link\" href=\"#id\"><span class=\"toc-text\">id</span></a><ol class=\"toc-child\"><li class=\"toc-item toc-level-3\"><a class=\"toc-link\" href=\"#-1\"><span class=\"toc-text\"></span></a></li></ol></li><li class=\"toc-item toc-level-2\"><a class=\"toc-link\" href=\"#whoami\"><span class=\"toc-text\">whoami</span></a></li><li class=\"toc-item toc-level-2\"><a class=\"toc-link\" href=\"#%E2%98%86ps-ef\"><span class=\"toc-text\">☆ps -ef</span></a></li><li class=\"toc-item toc-level-2\"><a class=\"toc-link\" href=\"#top\"><span class=\"toc-text\">top</span></a></li></ol></li><li class=\"toc-item toc-level-1\"><a class=\"toc-link\" href=\"#vi%E5%92%8Cvim%E7%BC%96%E8%BE%91%E5%99%A8\"><span class=\"toc-text\">vi和vim编辑器</span></a><ol class=\"toc-child\"><li class=\"toc-item toc-level-2\"><a class=\"toc-link\" href=\"#6-1-vi%E5%92%8Cvim%E7%9A%84%E5%9F%BA%E6%9C%AC%E4%BB%8B%E7%BB%8D\"><span class=\"toc-text\">6.1 vi和vim的基本介绍</span></a></li><li class=\"toc-item toc-level-2\"><a class=\"toc-link\" href=\"#6-2-%E4%B8%89%E7%A7%8D%E6%A8%A1%E5%BC%8F\"><span class=\"toc-text\">6.2 三种模式</span></a></li><li class=\"toc-item toc-level-2\"><a class=\"toc-link\" href=\"#6-3-vi%E5%92%8Cvim%E7%9A%84%E5%BF%AB%E6%8D%B7%E9%94%AE\"><span class=\"toc-text\">6.3 vi和vim的快捷键</span></a></li></ol></li></ol>","author":{"name":"Cencus","slug":"blog-author","avatar":"https://gitee.com/cencus/blog-image/raw/master/blogImage/1648381409561.jpg","link":"/","description":"stay hungry, stay foolish.","socials":{"github":"","twitter":"","stackoverflow":"","wechat":"","qq":"","weibo":"","zhihu":"","csdn":"","juejin":"","customs":{}}},"mapped":true,"prev_post":{"title":"flume","uid":"668b17fd878754e2652b25e78c8ab4f7","slug":"flume","date":"2022-03-31T13:03:51.085Z","updated":"2022-03-29T11:58:03.838Z","comments":true,"path":"api/articles/flume.json","keywords":null,"cover":[],"text":"我们不生产数据我们只是数据的搬运工 yum的配置三种source exec：不支持断点续传 spoolingdirector：不支持动态更新 taildirsource：解决上述两点，存在的问题重复上传&#x3D;&gt;不能更名，如果非要更名，只有改源码 改源码 tailfil...","link":"","photos":[],"count_time":{"symbolsCount":"6.6k","symbolsTime":"6 mins."},"categories":[],"tags":[],"author":{"name":"Cencus","slug":"blog-author","avatar":"https://gitee.com/cencus/blog-image/raw/master/blogImage/1648381409561.jpg","link":"/","description":"stay hungry, stay foolish.","socials":{"github":"","twitter":"","stackoverflow":"","wechat":"","qq":"","weibo":"","zhihu":"","csdn":"","juejin":"","customs":{}}}},"next_post":{"title":"kafka","uid":"464082c80523a34f8ff30e1785265886","slug":"kafka","date":"2022-03-29T06:02:54.000Z","updated":"2022-04-21T03:24:52.965Z","comments":true,"path":"api/articles/kafka.json","keywords":null,"cover":[],"text":"第一章 生产商，超市与消费者的爱恨情仇 1. 定义分布式，发布订阅，消息队列 2. 消息队列的应用场景 缓存消峰 解耦 异步通信 3.两种模式 点对点（一个生产者 一个消费者 一个主题 会删除数据） 发布订阅模式（多个生产者，多个消费者而且相互独立，多个主题，不会删除数据） 点对...","link":"","photos":[],"count_time":{"symbolsCount":"21k","symbolsTime":"19 mins."},"categories":[],"tags":[{"name":"大数据","slug":"大数据","count":3,"path":"api/tags/大数据.json"},{"name":"kafka","slug":"kafka","count":1,"path":"api/tags/kafka.json"}],"author":{"name":"Cencus","slug":"blog-author","avatar":"https://gitee.com/cencus/blog-image/raw/master/blogImage/1648381409561.jpg","link":"/","description":"stay hungry, stay foolish.","socials":{"github":"","twitter":"","stackoverflow":"","wechat":"","qq":"","weibo":"","zhihu":"","csdn":"","juejin":"","customs":{}}}}}